{
  "overlay_opacity": 0.0,
  "show_connection_status": false,
  "debug_overlay_corner": "SE",
  "client_log_retention": 5,
  "gridlines_enabled": false,
  "gridline_spacing": 100,
  "force_render": false,
  "allow_force_render_release": true,
  "force_xwayland": false,
  "show_debug_overlay": false,
  "min_font_point": 6.0,
  "max_font_point": 24.0,
  "status_bottom_margin": 30,
  "title_bar_enabled": false,
  "title_bar_height": 28,
  "cycle_payload_ids": false,
  "copy_payload_id_on_cycle": false,
  "scale_mode": "fill",
  "nudge_overflow_payloads": false,
  "payload_nudge_gutter": 20,
  "status_message_gutter": 10,
  "log_payloads": false,
  "payload_log_delay_seconds": 0.5
}